aiothrottle/__init__.py
aiothrottle/throttle.py
aiothrottle-0.1.3.dist-info/DESCRIPTION.rst
aiothrottle-0.1.3.dist-info/METADATA
aiothrottle-0.1.3.dist-info/RECORD
aiothrottle-0.1.3.dist-info/WHEEL
aiothrottle-0.1.3.dist-info/metadata.json
aiothrottle-0.1.3.dist-info/top_level.txt
