Metadata-Version: 2.0
Name: aiothrottle
Version: 0.1.3
Summary: Throttling, flow controlling StreamReader for aiohttp
Home-page: https://github.com/panda73111/aiothrottle
Author: Sebastian Hüther
Author-email: sebastian.huether@gmx.de
License: GPLv3
Download-URL: https://github.com/panda73111/aiothrottle/archive/v0.1.3.tar.gz
Keywords: throttle bandwidth limit download http throughput asyncio aiohttp
Platform: UNKNOWN
Classifier: Development Status :: 3 - Alpha
Classifier: Intended Audience :: Developers
Classifier: Topic :: Internet :: WWW/HTTP
Classifier: License :: OSI Approved :: GNU General Public License v3 (GPLv3)
Classifier: Programming Language :: Python
Classifier: Programming Language :: Python :: 3
Classifier: Programming Language :: Python :: 3.4
Classifier: Programming Language :: Python :: 3.5
Requires-Dist: aiohttp
